magurn/TorrentSearch.py
magurn/proxy.py
magurn-2.2.3.dist-info/METADATA
magurn-2.2.3.dist-info/WHEEL
magurn-2.2.3.dist-info/entry_points.txt
magurn-2.2.3.dist-info/top_level.txt
magurn-2.2.3.dist-info/RECORD
