Metadata-Version: 2.1
Name: magurn
Version: 2.2.3
Summary: A Torrent Search Client
Home-page: https://github.com/sgshivamgarg8/magurn
License: UNKNOWN
Platform: UNKNOWN
Classifier: Programming Language :: Python :: 3
Classifier: Operating System :: OS Independent
Requires-Dist: requests
Requires-Dist: bs4
Requires-Dist: pyperclip
Requires-Dist: colorama
